aspose/__init__.py
aspose/ocrmodels.cp310-win_amd64.pyd
aspose/ocrmodels.cp311-win_amd64.pyd
aspose/ocrmodels.cp35-win_amd64.pyd
aspose/ocrmodels.cp36-win_amd64.pyd
aspose/ocrmodels.cp37-win_amd64.pyd
aspose/ocrmodels.cp38-win_amd64.pyd
aspose/ocrmodels.cp39-win_amd64.pyd
aspose/pycore.cp310-win_amd64.pyd
aspose/pycore.cp311-win_amd64.pyd
aspose/pycore.cp35-win_amd64.pyd
aspose/pycore.cp36-win_amd64.pyd
aspose/pycore.cp37-win_amd64.pyd
aspose/pycore.cp38-win_amd64.pyd
aspose/pycore.cp39-win_amd64.pyd
aspose/pygc.cp310-win_amd64.pyd
aspose/pygc.cp311-win_amd64.pyd
aspose/pygc.cp35-win_amd64.pyd
aspose/pygc.cp36-win_amd64.pyd
aspose/pygc.cp37-win_amd64.pyd
aspose/pygc.cp38-win_amd64.pyd
aspose/pygc.cp39-win_amd64.pyd
aspose/pyreflection.cp310-win_amd64.pyd
aspose/pyreflection.cp311-win_amd64.pyd
aspose/pyreflection.cp35-win_amd64.pyd
aspose/pyreflection.cp36-win_amd64.pyd
aspose/pyreflection.cp37-win_amd64.pyd
aspose/pyreflection.cp38-win_amd64.pyd
aspose/pyreflection.cp39-win_amd64.pyd
aspose/__pyinstaller/__init__.pyi
aspose/__pyinstaller/hook-aspose.py
aspose/assemblies/ocrmodels/Aspose.OCR.Models.Handwritten.dll
aspose/assemblies/ocrmodels/WrpInterop.Aspose.OCRModels.dll
aspose/assemblies/pycore/WrpInterop.Aspose.PyCore.dll
aspose/assemblies/pygc/Aspose.PyGC.dll
aspose/assemblies/pyreflection/WrpInterop.Aspose.PyReflection.dll
aspose/netcore/netcore3.1/Microsoft.CSharp.dll
aspose/netcore/netcore3.1/Microsoft.DiaSymReader.Native.amd64.dll
aspose/netcore/netcore3.1/Microsoft.VisualBasic.Core.dll
aspose/netcore/netcore3.1/Microsoft.VisualBasic.dll
aspose/netcore/netcore3.1/Microsoft.Win32.Primitives.dll
aspose/netcore/netcore3.1/Microsoft.Win32.Registry.dll
aspose/netcore/netcore3.1/SOS_README.md
aspose/netcore/netcore3.1/System.AppContext.dll
aspose/netcore/netcore3.1/System.Buffers.dll
aspose/netcore/netcore3.1/System.Collections.Concurrent.dll
aspose/netcore/netcore3.1/System.Collections.Immutable.dll
aspose/netcore/netcore3.1/System.Collections.NonGeneric.dll
aspose_ocr_models_handwritten_python_net-23.12.1.dist-info/METADATA
aspose_ocr_models_handwritten_python_net-23.12.1.dist-info/WHEEL
aspose_ocr_models_handwritten_python_net-23.12.1.dist-info/entry_points.txt
aspose_ocr_models_handwritten_python_net-23.12.1.dist-info/top_level.txt
aspose_ocr_models_handwritten_python_net-23.12.1.dist-info/RECORD
